librec_auto/__init__.py
librec_auto/__main__.py
librec_auto/core/__init__.py
librec_auto/core/config_cmd.py
librec_auto/core/config_lib.py
librec_auto/core/cmd/.gitkeep
librec_auto/core/cmd/__init__.py
librec_auto/core/cmd/alg_cmd.py
librec_auto/core/cmd/check_cmd.py
librec_auto/core/cmd/cleanup_cmd.py
librec_auto/core/cmd/cmd.py
librec_auto/core/cmd/eval_cmd.py
librec_auto/core/cmd/librec_cmd.py
librec_auto/core/cmd/parallel_cmd.py
librec_auto/core/cmd/post_cmd.py
librec_auto/core/cmd/purge_cmd.py
librec_auto/core/cmd/rerank_cmd.py
librec_auto/core/cmd/setup_cmd.py
librec_auto/core/cmd/status_cmd.py
librec_auto/core/cmd/alg/ms_recommend_wrapper.py
librec_auto/core/cmd/eval/alpha-IA.py
librec_auto/core/cmd/eval/expected_exposure_metric.py
librec_auto/core/cmd/eval/ndcg_metric.py
librec_auto/core/cmd/eval/rmse_metric.py
librec_auto/core/cmd/eval/test_metric.py
librec_auto/core/cmd/post/.gitkeep
librec_auto/core/cmd/post/__init__.py
librec_auto/core/cmd/post/dropbox_post.py
librec_auto/core/cmd/post/result_graphics.py
librec_auto/core/cmd/post/results_to_csv.py
librec_auto/core/cmd/post/slack_post.py
librec_auto/core/cmd/rerank/.gitkeep
librec_auto/core/cmd/rerank/MCFSolve
librec_auto/core/cmd/rerank/__init__.py
librec_auto/core/cmd/rerank/cali_rerank.py
librec_auto/core/cmd/rerank/dm_rerank.py
librec_auto/core/cmd/rerank/fairstar_rerank.py
librec_auto/core/cmd/rerank/far_rerank.py
librec_auto/core/cmd/rerank/mmr_rerank.py
librec_auto/core/cmd/rerank/ofair_rerank.py
librec_auto/core/cmd/rerank/pfar_rerank.py
librec_auto/core/cmd/rerank/reranker.py
librec_auto/core/eval/__init__.py
librec_auto/core/eval/evaluator.py
librec_auto/core/eval/metrics/__init__.py
librec_auto/core/eval/metrics/list_based_metric.py
librec_auto/core/eval/metrics/row_based_metric.py
librec_auto/core/util/.gitkeep
librec_auto/core/util/BBO.py
librec_auto/core/util/README.md
librec_auto/core/util/__init__.py
librec_auto/core/util/encrypt.py
librec_auto/core/util/errors.py
librec_auto-0.2.13.dist-info/LICENSE
librec_auto-0.2.13.dist-info/LICENSE.txt
librec_auto-0.2.13.dist-info/METADATA
librec_auto-0.2.13.dist-info/WHEEL
librec_auto-0.2.13.dist-info/top_level.txt
librec_auto-0.2.13.dist-info/RECORD
