Metadata-Version: 2.1
Name: librec-auto
Version: 0.2.13
Summary: The librec-auto project aims to automate recommender system experiments using LibRec.
Home-page: https://github.com/that-recsys-lab/librec-auto
Author: Masoud Mansoury, Nasim Sonboli, Robin Burke, Will Mardick-Kanter and others
Author-email: masoodmansoury@gmail.com
License: UNKNOWN
Platform: UNKNOWN
Classifier: Programming Language :: Python :: 3
Classifier: License :: OSI Approved :: MIT License
Classifier: Operating System :: OS Independent
License-File: LICENSE
License-File: LICENSE.txt
Requires-Dist: matplotlib
Requires-Dist: pandas
Requires-Dist: numpy
Requires-Dist: progressbar
Requires-Dist: lxml
Requires-Dist: cryptography
Requires-Dist: slackclient (>=2.0)
Requires-Dist: slack
Requires-Dist: slacker
Requires-Dist: optuna
Requires-Dist: tensorflow
Requires-Dist: keras
Requires-Dist: torch
Requires-Dist: cornac
